{"type":"FeatureCollection","features":[{"type":"Feature","id":170586,"geometry":{"type":"Point","coordinates":[-91.50440200015268,44.806593789889938]},"properties":{"objectid":170586,"boundary":null,"comments":"Crews are in the area working to restore power as quickly and safely as possible. Please continue to check back for estimated restoration time updates. Thank you for your patience.","customers":1,"off_":1781319780000,"etr":1781330400000,"ticket":"13033631","outageimpact":"Small","outagetype":"Unplanned Outage","medialink":null,"outagestatus":0,"datastatus":null,"latlong":"5591124.853299998,-10186223.436","states":"WI","crewstatus":"Crew Onsite","globalid":"{58312E59-1A22-4553-A8DF-47253BF4A2E9}","county":"EAU CLAIRE","cause":"Outage","city":"Eau Claire","xcelarea":"Eau Claire"}},{"type":"Feature","id":170599,"geometry":{"type":"Point","coordinates":[-92.92448664996094,44.819145880136467]},"properties":{"objectid":170599,"boundary":null,"comments":"Crews are working to restore power as quickly and safely as possible. Please continue to check back for estimated restoration time updates. Thank you for your patience.","customers":147,"off_":1781324220000,"etr":1781337600000,"ticket":"13033631","outageimpact":"Medium","outagetype":"Unplanned Outage","medialink":null,"outagestatus":0,"datastatus":null,"latlong":"5593094.500600003,-10344306.5361","states":"MN","crewstatus":null,"globalid":"{88B3D668-622F-47DF-A28B-43E228129573}","county":"WASHINGTON","cause":"Outage","city":"Cottage Grove","xcelarea":"Cottage Grove"}},{"type":"Feature","id":170579,"geometry":{"type":"Point","coordinates":[-93.249715169620927,44.880640010303118]},"properties":{"objectid":170579,"boundary":null,"comments":"The outage has been reported. Please continue to check back for additional updates regarding the restoration progress.","customers":1,"off_":1781317080000,"etr":1781328600000,"ticket":"13033631","outageimpact":"Small","outagetype":"Unplanned Outage","medialink":null,"outagestatus":0,"datastatus":null,"latlong":"5602750.230700001,-10380510.8093","states":"MN","crewstatus":null,"globalid":"{6D0723A2-7279-4DE5-98DB-118A3428A8D7}","county":"HENNEPIN","cause":"Outage","city":"Richfield","xcelarea":"Richfield"}},{"type":"Feature","id":170501,"geometry":{"type":"Point","coordinates":[-92.782645659785004,44.949050380075228]},"properties":{"objectid":170501,"boundary":null,"comments":"The outage has been reported. Please continue to check back for additional updates regarding the restoration progress.","customers":2,"off_":1781300700000,"etr":1781344800000,"ticket":"13033631","outageimpact":"Small","outagetype":"Unplanned Outage","medialink":null,"outagestatus":0,"datastatus":null,"latlong":"5613504.0744,-10328516.8693","states":"MN","crewstatus":null,"globalid":"{CED499CB-2112-42F8-8C40-86CE6955A45B}","county":"WASHINGTON","cause":"Outage","city":"Afton","xcelarea":"Afton"}},{"type":"Feature","id":170300,"geometry":{"type":"Point","coordinates":[-93.011220339912242,44.825769159948202]},"properties":{"objectid":170300,"boundary":null,"comments":"The outage has been reported. Please continue to check back for additional updates regarding the restoration progress.","customers":2,"off_":1781288520000,"etr":1781325000000,"ticket":"13033631","outageimpact":"Small","outagetype":"Unplanned Outage","medialink":null,"outagestatus":0,"datastatus":null,"latlong":"5594133.984399997,-10353961.6863","states":"MN","crewstatus":null,"globalid":"{46710385-4F90-43F5-8B4F-EC86FF0CCD3A}","county":"DAKOTA","cause":"Outage","city":"Inver Grove","xcelarea":"Inver Grove"}},{"type":"Feature","id":170595,"geometry":{"type":"Point","coordinates":[-105.09674262008863,39.615413579865304]},"properties":{"objectid":170595,"boundary":null,"comments":"Crews are working to restore power as quickly and safely as possible. Please continue to check back for estimated restoration time updates. Thank you for your patience.","customers":45,"off_":1781320200000,"etr":1781328600000,"ticket":"13033631","outageimpact":"Small","outagetype":"Unplanned Outage","medialink":null,"outagestatus":0,"datastatus":null,"latlong":"4810211.6098000035,-11699315.872499999","states":"CO","crewstatus":null,"globalid":"{24D7A137-58C7-4D75-AB6D-35B2C0F94C43}","county":"JEFFERSON","cause":"Outage","city":"Littleton","xcelarea":"Littleton"}},{"type":"Feature","id":170513,"geometry":{"type":"Point","coordinates":[-93.104080799714339,44.834347069730093]},"properties":{"objectid":170513,"boundary":null,"comments":"The outage has been reported. Please continue to check back for additional updates regarding the restoration progress.","customers":1,"off_":1781301780000,"etr":1781344800000,"ticket":"13033631","outageimpact":"Small","outagetype":"Unplanned Outage","medialink":null,"outagestatus":0,"datastatus":null,"latlong":"5595480.413099997,-10364298.8654","states":"MN","crewstatus":null,"globalid":"{8DEC2F5F-D72E-4E0D-96AA-A30817CA1D77}","county":"DAKOTA","cause":"Outage","city":"Inver Grove Heights","xcelarea":"Inver Grove Heights"}},{"type":"Feature","id":170592,"geometry":{"type":"Point","coordinates":[-104.79758092016814,39.716990629990946]},"properties":{"objectid":170592,"boundary":null,"comments":"Crews are working to restore power as quickly and safely as possible. Please continue to check back for estimated restoration time updates. Thank you for your patience.","customers":3,"off_":1781317800000,"etr":1781325900000,"ticket":"13033631","outageimpact":"Small","outagetype":"Unplanned Outage","medialink":null,"outagestatus":0,"datastatus":null,"latlong":"4824900.955499999,-11666013.3444","states":"CO","crewstatus":null,"globalid":"{66AC1C65-ABEC-450E-93BF-C0283821340F}","county":"ARAPAHOE","cause":"Outage","city":"Aurora","xcelarea":"Aurora"}},{"type":"Feature","id":170596,"geometry":{"type":"Point","coordinates":[-92.651932170203708,45.053741989729339]},"properties":{"objectid":170596,"boundary":null,"comments":"Crews are working to restore power as quickly and safely as possible. Please continue to check back for estimated restoration time updates. Thank you for your patience.","customers":6,"off_":1781311740000,"etr":1781325900000,"ticket":"13033631","outageimpact":"Small","outagetype":"Unplanned Outage","medialink":null,"outagestatus":0,"datastatus":null,"latlong":"5629986.034199998,-10313965.9102","states":"WI","crewstatus":null,"globalid":"{D125BF55-89D6-4449-ACE5-E6D545E771F9}","county":"ST CROIX","cause":"Outage","city":"Hudson","xcelarea":"Hudson"}},{"type":"Feature","id":170594,"geometry":{"type":"Point","coordinates":[-92.630254100327505,44.990241580090739]},"properties":{"objectid":170594,"boundary":null,"comments":"Crews are working to restore power as quickly and safely as possible. Please continue to check back for estimated restoration time updates. Thank you for your patience.","customers":13,"off_":1781316000000,"etr":1781329500000,"ticket":"13033631","outageimpact":"Small","outagetype":"Unplanned Outage","medialink":null,"outagestatus":0,"datastatus":null,"latlong":"5619985.353500001,-10311552.7185","states":"WI","crewstatus":null,"globalid":"{73AC9561-DC64-4B0A-B611-FF71B7644D77}","county":"ST CROIX","cause":"Outage","city":"Hudson","xcelarea":"Hudson"}},{"type":"Feature","id":170552,"geometry":{"type":"Point","coordinates":[-105.16574947994094,39.812034419973443]},"properties":{"objectid":170552,"boundary":null,"comments":"Crews are working to restore power as quickly and safely as possible. Please continue to check back for estimated restoration time updates. Thank you for your patience.","customers":4,"off_":1781305740000,"etr":1781316000000,"ticket":"13033631","outageimpact":"Small","outagetype":"Unplanned Outage","medialink":null,"outagestatus":0,"datastatus":null,"latlong":"4838665.111400001,-11706997.681","states":"CO","crewstatus":null,"globalid":"{E7ADB50E-6A22-46A4-BBB8-9FA7EDECBF2A}","county":"JEFFERSON","cause":"Outage","city":"Arvada","xcelarea":"Arvada"}},{"type":"Feature","id":170570,"geometry":{"type":"Point","coordinates":[-92.963497319782149,44.879497460222915]},"properties":{"objectid":170570,"boundary":null,"comments":"Crews are working to restore power as quickly and safely as possible. Please continue to check back for estimated restoration time updates. Thank you for your patience.","customers":2,"off_":1781314260000,"etr":1781327700000,"ticket":"13033631","outageimpact":"Small","outagetype":"Unplanned Outage","medialink":null,"outagestatus":0,"datastatus":null,"latlong":"5602570.734899998,-10348649.184","states":"MN","crewstatus":null,"globalid":"{372C4C7F-A7F5-4DA8-8299-15CDD0BF0AD0}","county":"WASHINGTON","cause":"Outage","city":"Woodbury","xcelarea":"Woodbury"}},{"type":"Feature","id":170478,"geometry":{"type":"Point","coordinates":[-104.26072865041618,32.205950959658928]},"properties":{"objectid":170478,"boundary":null,"comments":"Crews are working to restore power as quickly and safely as possible. Please continue to check back for estimated restoration time updates. Thank you for your patience.","customers":5,"off_":1781295480000,"etr":1781308800000,"ticket":"13033631","outageimpact":"Small","outagetype":"Unplanned Outage","medialink":null,"outagestatus":0,"datastatus":null,"latlong":"3790375.355800003,-11606251.2231","states":"NM","crewstatus":null,"globalid":"{3F0CF2B2-3C88-4214-9ACC-CCF83AEA0247}","county":"EDDY-OUT","cause":"Outage","city":"Carlsbad","xcelarea":"Carlsbad"}},{"type":"Feature","id":170534,"geometry":{"type":"Point","coordinates":[-104.29497429035609,32.434913480192314]},"properties":{"objectid":170534,"boundary":null,"comments":"Crews are working to restore power as quickly and safely as possible. Please continue to check back for estimated restoration time updates. Thank you for your patience.","customers":1,"off_":1781297220000,"etr":1781325000000,"ticket":"13033631","outageimpact":"Small","outagetype":"Unplanned Outage","medialink":null,"outagestatus":0,"datastatus":null,"latlong":"3820536.152900003,-11610063.4303","states":"NM","crewstatus":null,"globalid":"{15D9295D-0E5E-4981-BF2D-F9256755A824}","county":"EDDY-OUT","cause":"Outage","city":"Carlsbad","xcelarea":"Carlsbad"}},{"type":"Feature","id":170473,"geometry":{"type":"Point","coordinates":[-91.754842080333901,45.404584510146158]},"properties":{"objectid":170473,"boundary":null,"comments":"Crews are working to restore power as quickly and safely as possible. Please continue to check back for estimated restoration time updates. Thank you for your patience.","customers":2,"off_":1781298600000,"etr":null,"ticket":"13033631","outageimpact":"Small","outagetype":"Unplanned Outage","medialink":null,"outagestatus":0,"datastatus":null,"latlong":"5685441.515900001,-10214102.2982","states":"WI","crewstatus":null,"globalid":"{B79651FD-D2EE-43D5-A1EB-5DA36BB94820}","county":"BARRON","cause":"Outage","city":"Cameron","xcelarea":"Cameron"}},{"type":"Feature","id":170267,"geometry":{"type":"Point","coordinates":[-93.143715629774732,44.953514550126457]},"properties":{"objectid":170267,"boundary":null,"comments":"The outage has been reported. Please continue to check back for additional updates regarding the restoration progress.","customers":1,"off_":1781286420000,"etr":1781339400000,"ticket":"13033631","outageimpact":"Small","outagetype":"Unplanned Outage","medialink":null,"outagestatus":0,"datastatus":null,"latlong":"5614206.2698,-10368710.9945","states":"MN","crewstatus":null,"globalid":"{47F8FD15-3ADB-48E1-A6E9-9624EA94B4F1}","county":"RAMSEY","cause":"Outage","city":"Saint Paul","xcelarea":"Saint Paul"}},{"type":"Feature","id":170591,"geometry":{"type":"Point","coordinates":[-101.96884192975384,35.86694829016951]},"properties":{"objectid":170591,"boundary":null,"comments":"Crews are working to restore power as quickly and safely as possible. Please continue to check back for estimated restoration time updates. Thank you for your patience.","customers":1,"off_":1781321640000,"etr":1781329500000,"ticket":"13033631","outageimpact":"Small","outagetype":"Unplanned Outage","medialink":null,"outagestatus":0,"datastatus":null,"latlong":"4282329.072300002,-11351119.5604","states":"TX","crewstatus":null,"globalid":"{9937FB76-E60C-4872-8224-BB185D690F07}","county":"MOORE","cause":"Outage","city":"Dumas","xcelarea":"Dumas"}},{"type":"Feature","id":170375,"geometry":{"type":"Point","coordinates":[-93.064747160395683,44.89351112979449]},"properties":{"objectid":170375,"boundary":null,"comments":"The outage has been reported. Please continue to check back for additional updates regarding the restoration progress.","customers":8,"off_":1781295720000,"etr":1781328600000,"ticket":"13033631","outageimpact":"Small","outagetype":"Unplanned Outage","medialink":null,"outagestatus":0,"datastatus":null,"latlong":"5604772.543200001,-10359920.2647","states":"MN","crewstatus":null,"globalid":"{0662F56F-E57C-43DD-A019-D8184398FDB2}","county":"DAKOTA","cause":"Outage","city":"Saint Paul,  South Saint Paul","xcelarea":"Saint Paul,  South Saint Paul"}},{"type":"Feature","id":170555,"geometry":{"type":"Point","coordinates":[-104.30670839990594,32.442365159705695]},"properties":{"objectid":170555,"boundary":null,"comments":"Crews are working to restore power as quickly and safely as possible. Please continue to check back for estimated restoration time updates. Thank you for your patience.","customers":1,"off_":1781297220000,"etr":1781323200000,"ticket":"13033631","outageimpact":"Small","outagetype":"Unplanned Outage","medialink":null,"outagestatus":0,"datastatus":null,"latlong":"3821519.032300003,-11611369.6654","states":"NM","crewstatus":null,"globalid":"{6051300D-E813-47A7-B589-DE3FE9022CF6}","county":"EDDY-OUT","cause":"Outage","city":"Carlsbad","xcelarea":"Carlsbad"}},{"type":"Feature","id":170506,"geometry":{"type":"Point","coordinates":[-101.44563005028017,36.18262098971195]},"properties":{"objectid":170506,"boundary":null,"comments":"Crews are in the area working to restore power as quickly and safely as possible. Please continue to check back for estimated restoration time updates. Thank you for your patience.","customers":26,"off_":1781301180000,"etr":1781360100000,"ticket":"13033631","outageimpact":"Small","outagetype":"Unplanned Outage","medialink":null,"outagestatus":0,"datastatus":null,"latlong":"4325778.921599999,-11292875.8804","states":"TX","crewstatus":"Crew Onsite","globalid":"{5E8B9A8E-8379-4E86-B82F-7F9BD5041F8C}","county":"HANSFORD, HUTCHINSON","cause":"Outage","city":"Gruver","xcelarea":"Gruver"}},{"type":"Feature","id":170537,"geometry":{"type":"Point","coordinates":[-93.307125029785212,44.98963499018803]},"properties":{"objectid":170537,"boundary":null,"comments":"Crews are in the area working to restore power as quickly and safely as possible. Please continue to check back for estimated restoration time updates. Thank you for your patience.","customers":11,"off_":1781295060000,"etr":1781330400000,"ticket":"13033631","outageimpact":"Small","outagetype":"Unplanned Outage","medialink":null,"outagestatus":0,"datastatus":null,"latlong":"5619889.875100002,-10386901.6457","states":"MN","crewstatus":"Crew Onsite","globalid":"{58486BCA-700D-45F1-8BED-E9BD6908FFAB}","county":"HENNEPIN","cause":"Outage","city":"Minneapolis","xcelarea":"Minneapolis"}},{"type":"Feature","id":170568,"geometry":{"type":"Point","coordinates":[-93.370197229900086,44.960736369835686]},"properties":{"objectid":170568,"boundary":null,"comments":"Crews are working to restore power as quickly and safely as possible. Please continue to check back for estimated restoration time updates. Thank you for your patience.","customers":1,"off_":1781313420000,"etr":1781325000000,"ticket":"13033631","outageimpact":"Small","outagetype":"Unplanned Outage","medialink":null,"outagestatus":0,"datastatus":null,"latlong":"5615342.3477,-10393922.8109","states":"MN","crewstatus":null,"globalid":"{1B882ED9-BA48-4007-BCF6-24B3F6BB4559}","county":"HENNEPIN","cause":"Outage","city":"Saint Louis Park","xcelarea":"Saint Louis Park"}},{"type":"Feature","id":170507,"geometry":{"type":"Point","coordinates":[-93.512936120338509,44.931313720166365]},"properties":{"objectid":170507,"boundary":null,"comments":"Crews are working to restore power as quickly and safely as possible. Please continue to check back for estimated restoration time updates. Thank you for your patience.","customers":18,"off_":1781294040000,"etr":1781333100000,"ticket":"13033631","outageimpact":"Small","outagetype":"Unplanned Outage","medialink":null,"outagestatus":0,"datastatus":null,"latlong":"5610714.710900001,-10409812.4315","states":"MN","crewstatus":null,"globalid":"{61F6AADD-4B52-44BD-8364-95EC161A281E}","county":"HENNEPIN","cause":"Outage","city":"Wayzata,  Deephaven,  Excelsior","xcelarea":"Wayzata,  Deephaven,  Excelsior"}},{"type":"Feature","id":170412,"geometry":{"type":"Point","coordinates":[-104.9769221896775,39.541090810034326]},"properties":{"objectid":170412,"boundary":null,"comments":"Crews are working to restore power as quickly and safely as possible. Please continue to check back for estimated restoration time updates. Thank you for your patience.","customers":7,"off_":1781292900000,"etr":1781313300000,"ticket":"13033631","outageimpact":"Small","outagetype":"Unplanned Outage","medialink":null,"outagestatus":0,"datastatus":null,"latlong":"4799477.235299997,-11685977.5232","states":"CO","crewstatus":null,"globalid":"{0ABB514F-78E4-484E-BF08-638C9B218B10}","county":"DOUGLAS","cause":"Outage","city":"Littleton","xcelarea":"Littleton"}},{"type":"Feature","id":170517,"geometry":{"type":"Point","coordinates":[-92.999154450188627,44.870027350190263]},"properties":{"objectid":170517,"boundary":null,"comments":"Crews are working to restore power as quickly and safely as possible. Please continue to check back for estimated restoration time updates. Thank you for your patience.","customers":1,"off_":1781302440000,"etr":1781344800000,"ticket":"13033631","outageimpact":"Small","outagetype":"Unplanned Outage","medialink":null,"outagestatus":0,"datastatus":null,"latlong":"5601083.108000003,-10352618.5176","states":"MN","crewstatus":null,"globalid":"{5CBD198B-58C1-44EF-BCB1-6FAF94C5D84B}","county":"WASHINGTON","cause":"Outage","city":"Newport","xcelarea":"Newport"}},{"type":"Feature","id":170340,"geometry":{"type":"Point","coordinates":[-92.785960209621422,45.280773960057793]},"properties":{"objectid":170340,"boundary":null,"comments":"Crews are working to restore power as quickly and safely as possible. Please continue to check back for estimated restoration time updates. Thank you for your patience.","customers":1,"off_":1781293260000,"etr":1781337600000,"ticket":"13033631","outageimpact":"Small","outagetype":"Unplanned Outage","medialink":null,"outagestatus":0,"datastatus":null,"latlong":"5665832.437600002,-10328885.8433","states":"MN","crewstatus":null,"globalid":"{396079DC-F1F8-4F32-ACF9-F6FC02F4F5B5}","county":"WASHINGTON","cause":"Outage","city":"Scandia","xcelarea":"Scandia"}},{"type":"Feature","id":170283,"geometry":{"type":"Point","coordinates":[-93.014037589593912,44.834217880054375]},"properties":{"objectid":170283,"boundary":null,"comments":"The outage has been reported. Please continue to check back for additional updates regarding the restoration progress.","customers":3,"off_":1781287380000,"etr":null,"ticket":"13033631","outageimpact":"Small","outagetype":"Unplanned Outage","medialink":null,"outagestatus":0,"datastatus":null,"latlong":"5595460.133400001,-10354275.3011","states":"MN","crewstatus":null,"globalid":"{CECE2B5A-1170-4283-9D80-F6C317CD243D}","county":"DAKOTA","cause":"Outage","city":"Inver Grove Heights,  Inver Grove","xcelarea":"Inver Grove Heights,  Inver Grove"}},{"type":"Feature","id":170488,"geometry":{"type":"Point","coordinates":[-93.175144869839244,45.017689250077275]},"properties":{"objectid":170488,"boundary":null,"comments":"Crews are in the area working to restore power as quickly and safely as possible. Please continue to check back for estimated restoration time updates. Thank you for your patience.","customers":30,"off_":1781299440000,"etr":1781328600000,"ticket":"13033631","outageimpact":"Small","outagetype":"Unplanned Outage","medialink":null,"outagestatus":0,"datastatus":null,"latlong":"5624306.726599999,-10372209.6815","states":"MN","crewstatus":"Crew Onsite","globalid":"{BB468D83-CB1B-40AC-AB19-BD982A1AC453}","county":"RAMSEY","cause":"Outage","city":"Roseville","xcelarea":"Roseville"}},{"type":"Feature","id":170575,"geometry":{"type":"Point","coordinates":[-93.080570570002095,45.092405769825554]},"properties":{"objectid":170575,"boundary":null,"comments":"Crews are working to restore power as quickly and safely as possible. Please continue to check back for estimated restoration time updates. Thank you for your patience.","customers":10,"off_":1781313720000,"etr":1781336700000,"ticket":"13033631","outageimpact":"Small","outagetype":"Unplanned Outage","medialink":null,"outagestatus":0,"datastatus":null,"latlong":"5636080.633299999,-10361681.7186","states":"MN","crewstatus":null,"globalid":"{DCAF5ED3-42C2-4C99-8CEA-750DEAB3E2A1}","county":"RAMSEY","cause":"Outage","city":"North Oaks","xcelarea":"North Oaks"}},{"type":"Feature","id":170477,"geometry":{"type":"Point","coordinates":[-93.121433670143716,44.888946729756498]},"properties":{"objectid":170477,"boundary":null,"comments":"The outage has been reported. Please continue to check back for additional updates regarding the restoration progress.","customers":11,"off_":1781298780000,"etr":1781323200000,"ticket":"13033631","outageimpact":"Small","outagetype":"Unplanned Outage","medialink":null,"outagestatus":0,"datastatus":null,"latlong":"5604055.3320999965,-10366230.5781","states":"MN","crewstatus":null,"globalid":"{0038E1CC-1BC2-44C5-B563-468432AAAE97}","county":"DAKOTA","cause":"Outage","city":"Mendota Heights","xcelarea":"Mendota Heights"}},{"type":"Feature","id":170516,"geometry":{"type":"Point","coordinates":[-91.069745230208824,45.472851519771538]},"properties":{"objectid":170516,"boundary":null,"comments":"Crews are working to restore power as quickly and safely as possible. Please continue to check back for estimated restoration time updates. Thank you for your patience.","customers":8,"off_":1781301480000,"etr":1781311500000,"ticket":"13033631","outageimpact":"Small","outagetype":"Unplanned Outage","medialink":null,"outagestatus":0,"datastatus":null,"latlong":"5696272.0079,-10137837.6657","states":"WI","crewstatus":null,"globalid":"{3E00099C-15CE-4FA5-82ED-3029977217B0}","county":"RUSK","cause":"Outage","city":"Ladysmith","xcelarea":"Ladysmith"}},{"type":"Feature","id":170566,"geometry":{"type":"Point","coordinates":[-93.283586629803963,44.957605470239052]},"properties":{"objectid":170566,"boundary":null,"comments":"The outage has been reported. Please continue to check back for additional updates regarding the restoration progress.","customers":44,"off_":1781308800000,"etr":1781322300000,"ticket":"13033631","outageimpact":"Small","outagetype":"Unplanned Outage","medialink":null,"outagestatus":0,"datastatus":null,"latlong":"5614849.802500002,-10384281.363","states":"MN","crewstatus":null,"globalid":"{9362D665-2966-4117-8D25-F604E3521ECA}","county":"HENNEPIN","cause":"Outage","city":"Minneapolis","xcelarea":"Minneapolis"}},{"type":"Feature","id":170493,"geometry":{"type":"Point","coordinates":[-104.26988571979135,32.222147650266031]},"properties":{"objectid":170493,"boundary":null,"comments":"Crews are working to restore power as quickly and safely as possible. Please continue to check back for estimated restoration time updates. Thank you for your patience.","customers":1,"off_":1781296560000,"etr":1781308800000,"ticket":"13033631","outageimpact":"Small","outagetype":"Unplanned Outage","medialink":null,"outagestatus":0,"datastatus":null,"latlong":"3792506.412799999,-11607270.5834","states":"NM","crewstatus":null,"globalid":"{5F05D5AD-9DF1-445E-9493-AAABF7D12ADA}","county":"EDDY-OUT","cause":"Outage","city":"Carlsbad","xcelarea":"Carlsbad"}},{"type":"Feature","id":170489,"geometry":{"type":"Point","coordinates":[-104.25048243035293,32.490149389684227]},"properties":{"objectid":170489,"boundary":null,"comments":"Crews are in the area working to restore power as quickly and safely as possible. Please continue to check back for estimated restoration time updates. Thank you for your patience.","customers":1,"off_":1781296200000,"etr":1781326800000,"ticket":"13033631","outageimpact":"Small","outagetype":"Unplanned Outage","medialink":null,"outagestatus":0,"datastatus":null,"latlong":"3827823.723200001,-11605110.6191","states":"NM","crewstatus":"Crew Onsite","globalid":"{BC069425-E893-4665-9773-7C9F4ACDA717}","county":"EDDY-OUT","cause":"Outage","city":"Carlsbad","xcelarea":"Carlsbad"}},{"type":"Feature","id":170271,"geometry":{"type":"Point","coordinates":[-105.05758823958493,40.009790989925342]},"properties":{"objectid":170271,"boundary":null,"comments":"Crews are working to restore power as quickly and safely as possible. Please continue to check back for estimated restoration time updates. Thank you for your patience.","customers":1,"off_":1781283000000,"etr":1781291700000,"ticket":"13033631","outageimpact":"Small","outagetype":"Unplanned Outage","medialink":null,"outagestatus":0,"datastatus":null,"latlong":"4867365.181500003,-11694957.2268","states":"CO","crewstatus":null,"globalid":"{D6F1C2FC-E521-402E-80AD-92B706DFA33B}","county":"BOULDER","cause":"Outage","city":"Erie","xcelarea":"Erie"}},{"type":"Feature","id":170104,"geometry":{"type":"Point","coordinates":[-93.114220379871938,44.971425830086538]},"properties":{"objectid":170104,"boundary":null,"comments":"The outage has been reported. Please continue to check back for additional updates regarding the restoration progress.","customers":1,"off_":1781276160000,"etr":1781346600000,"ticket":"13033631","outageimpact":"Small","outagetype":"Unplanned Outage","medialink":null,"outagestatus":0,"datastatus":null,"latlong":"5617024.189099997,-10365427.5983","states":"MN","crewstatus":null,"globalid":"{F750D671-DDF1-4EAF-803D-6790A1CA9138}","county":"RAMSEY","cause":"Outage","city":"Saint Paul","xcelarea":"Saint Paul"}},{"type":"Feature","id":170405,"geometry":{"type":"Point","coordinates":[-93.097803090437921,44.850566509991928]},"properties":{"objectid":170405,"boundary":null,"comments":"The outage has been reported. Please continue to check back for additional updates regarding the restoration progress.","customers":5,"off_":1781296020000,"etr":1781320500000,"ticket":"13033631","outageimpact":"Small","outagetype":"Unplanned Outage","medialink":null,"outagestatus":0,"datastatus":null,"latlong":"5598026.839900002,-10363600.034","states":"MN","crewstatus":null,"globalid":"{431BBB22-7296-4ADB-BD17-E8AA9D9724CB}","county":"DAKOTA","cause":"Outage","city":"Inver Grove Heights","xcelarea":"Inver Grove Heights"}},{"type":"Feature","id":170254,"geometry":{"type":"Point","coordinates":[-108.60268124969278,39.086341039948316]},"properties":{"objectid":170254,"boundary":null,"comments":"Crews are working to restore power as quickly and safely as possible. Please continue to check back for estimated restoration time updates. Thank you for your patience.","customers":2,"off_":1781275140000,"etr":null,"ticket":"13033631","outageimpact":"Small","outagetype":"Unplanned Outage","medialink":null,"outagestatus":0,"datastatus":null,"latlong":"4734046.742600001,-12089595.1755","states":"CO","crewstatus":null,"globalid":"{C1792EB4-36EE-40DA-A7B1-B37344CD69E0}","county":"MESA","cause":"Outage","city":"Grand Junction","xcelarea":"Grand Junction"}},{"type":"Feature","id":170406,"geometry":{"type":"Point","coordinates":[-93.037779180407568,44.832235979833733]},"properties":{"objectid":170406,"boundary":null,"comments":"Crews are working to restore power as quickly and safely as possible. Please continue to check back for estimated restoration time updates. Thank you for your patience.","customers":10,"off_":1781296200000,"etr":1781318700000,"ticket":"13033631","outageimpact":"Small","outagetype":"Unplanned Outage","medialink":null,"outagestatus":0,"datastatus":null,"latlong":"5595149.027999997,-10356918.2029","states":"MN","crewstatus":null,"globalid":"{CFA9D336-B928-459F-8B0F-5DBC3D188206}","county":"DAKOTA","cause":"Outage","city":"Inver Grove Heights","xcelarea":"Inver Grove Heights"}},{"type":"Feature","id":170409,"geometry":{"type":"Point","coordinates":[-93.034249629587663,44.962673339989657]},"properties":{"objectid":170409,"boundary":null,"comments":"The outage has been reported. Please continue to check back for additional updates regarding the restoration progress.","customers":1,"off_":1781296260000,"etr":1781320500000,"ticket":"13033631","outageimpact":"Small","outagetype":"Unplanned Outage","medialink":null,"outagestatus":0,"datastatus":null,"latlong":"5615647.0803999975,-10356525.2951","states":"MN","crewstatus":null,"globalid":"{962B8223-23A3-4359-8C59-E4AFE17FE1E3}","county":"RAMSEY","cause":"Outage","city":"Saint Paul","xcelarea":"Saint Paul"}},{"type":"Feature","id":170357,"geometry":{"type":"Point","coordinates":[-93.363457439817907,44.90333528981548]},"properties":{"objectid":170357,"boundary":null,"comments":"Crews are in the area working to restore power as quickly and safely as possible. Please continue to check back for estimated restoration time updates. Thank you for your patience.","customers":53,"off_":1781294400000,"etr":1781328600000,"ticket":"13033631","outageimpact":"Small","outagetype":"Unplanned Outage","medialink":null,"outagestatus":0,"datastatus":null,"latlong":"5606316.421499997,-10393172.5409","states":"MN","crewstatus":"Crew Onsite","globalid":"{0B392081-5151-48F7-80A9-BD7A532624C2}","county":"HENNEPIN","cause":"Outage","city":"Edina","xcelarea":"Edina"}},{"type":"Feature","id":165773,"geometry":{"type":"Point","coordinates":[-101.93681799958135,35.150564280109386]},"properties":{"objectid":165773,"boundary":null,"comments":"Crews are working to restore power as quickly and safely as possible. Please continue to check back for estimated restoration time updates. Thank you for your patience.","customers":1,"off_":1780993800000,"etr":1781275500000,"ticket":"13033631","outageimpact":"Small","outagetype":"Unplanned Outage","medialink":null,"outagestatus":0,"datastatus":null,"latlong":"4184361.099600002,-11347554.6728","states":"TX","crewstatus":null,"globalid":"{C93AC54A-ED9F-4FAA-84A3-B4F828518540}","county":"RANDALL","cause":"Outage","city":"Amarillo","xcelarea":"Amarillo"}}]}