{"type":"FeatureCollection","features":[{"type":"Feature","id":182940,"geometry":{"type":"Point","coordinates":[-104.92118200028403,39.708886610100365]},"properties":{"objectid":182940,"boundary":null,"comments":"The outage has been reported. Please continue to check back for additional updates regarding the restoration progress.","customers":1,"off_":1782357600000,"etr":1782381600000,"ticket":"25034831","outageimpact":"Small","outagetype":"Unplanned Outage","medialink":null,"outagestatus":0,"datastatus":null,"latlong":"4823728.2168999985,-11679772.5537","states":"CO","crewstatus":null,"globalid":"{437ABED3-5489-46B8-AFD1-C6C760DE8FE7}","county":"DENVER","cause":"Outage","city":"Denver","xcelarea":"Denver"}},{"type":"Feature","id":182908,"geometry":{"type":"Point","coordinates":[-104.89295669959671,40.465572049665859]},"properties":{"objectid":182908,"boundary":null,"comments":"Crews are working to restore power as quickly and safely as possible. Please continue to check back for estimated restoration time updates. Thank you for your patience.","customers":83,"off_":1782356280000,"etr":1782364500000,"ticket":"25034831","outageimpact":"Small","outagetype":"Unplanned Outage","medialink":null,"outagestatus":0,"datastatus":null,"latlong":"4933830.394900002,-11676630.5276","states":"CO","crewstatus":null,"globalid":"{A335B34F-6D29-453E-8447-CF89B072B9A3}","county":"WELD","cause":"Outage","city":"Windsor","xcelarea":"Windsor"}},{"type":"Feature","id":182884,"geometry":{"type":"Point","coordinates":[-105.00833744027807,39.685927440256584]},"properties":{"objectid":182884,"boundary":null,"comments":"The outage has been reported. Please continue to check back for additional updates regarding the restoration progress.","customers":141,"off_":1782338040000,"etr":1782356400000,"ticket":"25034831","outageimpact":"Medium","outagetype":"Unplanned Outage","medialink":null,"outagestatus":0,"datastatus":null,"latlong":"4820406.526500002,-11689474.6529","states":"CO","crewstatus":null,"globalid":"{5F95F427-AC06-46C2-9419-4F243A3636FD}","county":"DENVER, ARAPAHOE","cause":"Outage","city":"Englewood,  Denver","xcelarea":"Englewood,  Denver"}},{"type":"Feature","id":182786,"geometry":{"type":"Point","coordinates":[-105.09906626977619,39.763028099777713]},"properties":{"objectid":182786,"boundary":null,"comments":"Crews are working to restore power as quickly and safely as possible. Please continue to check back for estimated restoration time updates. Thank you for your patience.","customers":1,"off_":1782344460000,"etr":1782360000000,"ticket":"25034831","outageimpact":"Small","outagetype":"Unplanned Outage","medialink":null,"outagestatus":0,"datastatus":null,"latlong":"4831565.687799998,-11699574.54","states":"CO","crewstatus":null,"globalid":"{86305A8E-D2B3-42BE-ABD3-EF75A528FA70}","county":"JEFFERSON","cause":"Outage","city":"Wheat Ridge","xcelarea":"Wheat Ridge"}},{"type":"Feature","id":182587,"geometry":{"type":"Point","coordinates":[-105.10275685978044,39.604096229707807]},"properties":{"objectid":182587,"boundary":null,"comments":"Crews are working to restore power as quickly and safely as possible. Please continue to check back for estimated restoration time updates. Thank you for your patience.","customers":49,"off_":1782337980000,"etr":1782360000000,"ticket":"25034831","outageimpact":"Small","outagetype":"Unplanned Outage","medialink":null,"outagestatus":0,"datastatus":null,"latlong":"4808576.311300002,-11699985.3746","states":"CO","crewstatus":null,"globalid":"{AFFD7176-CBD8-441A-8CE5-4232CF9ED9BC}","county":"JEFFERSON","cause":"Outage","city":"Littleton","xcelarea":"Littleton"}},{"type":"Feature","id":182868,"geometry":{"type":"Point","coordinates":[-104.98641885995929,39.67669237030649]},"properties":{"objectid":182868,"boundary":null,"comments":"The outage has been reported. Please continue to check back for additional updates regarding the restoration progress.","customers":1,"off_":1782348480000,"etr":1782356400000,"ticket":"25034831","outageimpact":"Small","outagetype":"Unplanned Outage","medialink":null,"outagestatus":0,"datastatus":null,"latlong":"4819070.725100003,-11687034.6877","states":"CO","crewstatus":null,"globalid":"{3E62D06E-C615-4E87-A2B1-F4DC3384D6D4}","county":"DENVER","cause":"Outage","city":"Denver","xcelarea":"Denver"}},{"type":"Feature","id":182901,"geometry":{"type":"Point","coordinates":[-105.00653307970681,39.65495325025546]},"properties":{"objectid":182901,"boundary":null,"comments":"The outage has been reported. Please continue to check back for additional updates regarding the restoration progress.","customers":1,"off_":1782354120000,"etr":1782362700000,"ticket":"25034831","outageimpact":"Small","outagetype":"Unplanned Outage","medialink":null,"outagestatus":0,"datastatus":null,"latlong":"4815926.987400003,-11689273.792399999","states":"CO","crewstatus":null,"globalid":"{47DDA450-4981-4362-8A9E-8E1028E7A48D}","county":"ARAPAHOE","cause":"Outage","city":"Sheridan","xcelarea":"Sheridan"}},{"type":"Feature","id":182883,"geometry":{"type":"Point","coordinates":[-105.36807340039279,39.602798620031379]},"properties":{"objectid":182883,"boundary":null,"comments":"Crews are in the area working to restore power as quickly and safely as possible. Please continue to check back for estimated restoration time updates. Thank you for your patience.","customers":1,"off_":1782350760000,"etr":1782364500000,"ticket":"25034831","outageimpact":"Small","outagetype":"Unplanned Outage","medialink":null,"outagestatus":0,"datastatus":null,"latlong":"4808388.830499999,-11729520.2768","states":"CO","crewstatus":"Crew Onsite","globalid":"{E21BD05B-5B01-496E-AFE9-FA955DD19980}","county":"JEFFERSON","cause":"Outage","city":"Evergreen","xcelarea":"Evergreen"}},{"type":"Feature","id":182920,"geometry":{"type":"Point","coordinates":[-102.35405268030995,33.940715669862485]},"properties":{"objectid":182920,"boundary":null,"comments":"Crews are working to restore power as quickly and safely as possible. Please continue to check back for estimated restoration time updates. Thank you for your patience.","customers":248,"off_":1782349860000,"etr":null,"ticket":"25034831","outageimpact":"Medium","outagetype":"Unplanned Outage","medialink":null,"outagestatus":0,"datastatus":null,"latlong":"4020844.3642000034,-11394001.025","states":"TX","crewstatus":null,"globalid":"{A48015AD-19EE-45BD-8DF1-0E81CDF07085}","county":"LAMB","cause":"Outage","city":"Littlefield","xcelarea":"Littlefield"}},{"type":"Feature","id":182943,"geometry":{"type":"Point","coordinates":[-105.09318650967906,39.772069749873552]},"properties":{"objectid":182943,"boundary":null,"comments":"The outage has been reported. Please continue to check back for additional updates regarding the restoration progress.","customers":1,"off_":1782358980000,"etr":1782369900000,"ticket":"25034831","outageimpact":"Small","outagetype":"Unplanned Outage","medialink":null,"outagestatus":0,"datastatus":null,"latlong":"4832875.148800001,-11698920.0081","states":"CO","crewstatus":null,"globalid":"{83E8AB45-B1A5-486C-9A01-6A06A957CE85}","county":"JEFFERSON","cause":"Outage","city":"Wheat Ridge","xcelarea":"Wheat Ridge"}},{"type":"Feature","id":182941,"geometry":{"type":"Point","coordinates":[-104.99823894995991,39.651850739938695]},"properties":{"objectid":182941,"boundary":null,"comments":"Crews are working to restore power as quickly and safely as possible. Please continue to check back for estimated restoration time updates. Thank you for your patience.","customers":4,"off_":1782340680000,"etr":1782360000000,"ticket":"25034831","outageimpact":"Small","outagetype":"Unplanned Outage","medialink":null,"outagestatus":0,"datastatus":null,"latlong":"4815478.407799996,-11688350.4941","states":"CO","crewstatus":null,"globalid":"{730D8278-763C-4429-BD66-24FBBC2A69C7}","county":"ARAPAHOE","cause":"Outage","city":"Englewood","xcelarea":"Englewood"}},{"type":"Feature","id":182942,"geometry":{"type":"Point","coordinates":[-104.89329705957977,40.468687919696812]},"properties":{"objectid":182942,"boundary":null,"comments":"Crews are working to restore power as quickly and safely as possible. Please continue to check back for estimated restoration time updates. Thank you for your patience.","customers":1,"off_":1782356400000,"etr":1782364500000,"ticket":"25034831","outageimpact":"Small","outagetype":"Unplanned Outage","medialink":null,"outagestatus":0,"datastatus":null,"latlong":"4934286.318800002,-11676668.416299999","states":"CO","crewstatus":null,"globalid":"{BE1D0D36-85B0-45A3-BE1E-A9CA72058673}","county":"WELD","cause":"Outage","city":"Windsor","xcelarea":"Windsor"}},{"type":"Feature","id":182927,"geometry":{"type":"Point","coordinates":[-101.38054254001248,35.344050549838251]},"properties":{"objectid":182927,"boundary":null,"comments":"Crews are working to restore power as quickly and safely as possible. Please continue to check back for estimated restoration time updates. Thank you for your patience.","customers":1,"off_":1782353340000,"etr":null,"ticket":"25034831","outageimpact":"Small","outagetype":"Unplanned Outage","medialink":null,"outagestatus":0,"datastatus":null,"latlong":"4210735.092,-11285630.3719","states":"TX","crewstatus":null,"globalid":"{31C9D8C7-EC74-4C7E-970F-FB08FFEBC00B}","county":"CARSON","cause":"Outage","city":"Panhandle","xcelarea":"Panhandle"}},{"type":"Feature","id":182915,"geometry":{"type":"Point","coordinates":[-101.77563115016142,35.228534439741502]},"properties":{"objectid":182915,"boundary":null,"comments":"Crews are working to restore power as quickly and safely as possible. Please continue to check back for estimated restoration time updates. Thank you for your patience.","customers":11,"off_":1782349080000,"etr":1782369000000,"ticket":"25034831","outageimpact":"Small","outagetype":"Unplanned Outage","medialink":null,"outagestatus":0,"datastatus":null,"latlong":"4194981.5945999995,-11329611.4348","states":"TX","crewstatus":null,"globalid":"{963F9BE4-DA1E-4661-907A-5F010F250297}","county":"POTTER","cause":"Outage","city":"Amarillo","xcelarea":"Amarillo"}},{"type":"Feature","id":182709,"geometry":{"type":"Point","coordinates":[-105.02509687015603,39.631092660324754]},"properties":{"objectid":182709,"boundary":null,"comments":"The outage has been reported. Please continue to check back for additional updates regarding the restoration progress.","customers":82,"off_":1782338520000,"etr":1782358200000,"ticket":"25034831","outageimpact":"Small","outagetype":"Unplanned Outage","medialink":null,"outagestatus":0,"datastatus":null,"latlong":"4812477.597599998,-11691340.3041","states":"CO","crewstatus":null,"globalid":"{B7C612E8-950F-45E4-8934-754EAD370F68}","county":"DENVER","cause":"Outage","city":"Denver,  Englewood","xcelarea":"Denver,  Englewood"}},{"type":"Feature","id":182787,"geometry":{"type":"Point","coordinates":[-105.11263270984198,39.768430400308581]},"properties":{"objectid":182787,"boundary":null,"comments":"Crews are working to restore power as quickly and safely as possible. Please continue to check back for estimated restoration time updates. Thank you for your patience.","customers":1,"off_":1782344400000,"etr":1782360000000,"ticket":"25034831","outageimpact":"Small","outagetype":"Unplanned Outage","medialink":null,"outagestatus":0,"datastatus":null,"latlong":"4832348.057700001,-11701084.749200001","states":"CO","crewstatus":null,"globalid":"{BABA5924-03DB-4080-9D52-24C3981D3AC2}","county":"JEFFERSON","cause":"Outage","city":"Wheat Ridge","xcelarea":"Wheat Ridge"}},{"type":"Feature","id":182917,"geometry":{"type":"Point","coordinates":[-101.88892622014534,34.76694351011222]},"properties":{"objectid":182917,"boundary":null,"comments":"Crews are working to restore power as quickly and safely as possible. Please continue to check back for estimated restoration time updates. Thank you for your patience.","customers":1,"off_":1782348360000,"etr":null,"ticket":"25034831","outageimpact":"Small","outagetype":"Unplanned Outage","medialink":null,"outagestatus":0,"datastatus":null,"latlong":"4132254.6283000037,-11342223.3843","states":"TX","crewstatus":null,"globalid":"{FCD8463E-4919-48D9-B402-83F871FA1E92}","county":"RANDALL","cause":"Outage","city":"Happy","xcelarea":"Happy"}},{"type":"Feature","id":182918,"geometry":{"type":"Point","coordinates":[-101.87364184013359,35.198836540156307]},"properties":{"objectid":182918,"boundary":null,"comments":"Crews are working to restore power as quickly and safely as possible. Please continue to check back for estimated restoration time updates. Thank you for your patience.","customers":9,"off_":1782299760000,"etr":null,"ticket":"25034831","outageimpact":"Small","outagetype":"Unplanned Outage","medialink":null,"outagestatus":0,"datastatus":null,"latlong":"4190935.1735000014,-11340521.9349","states":"TX","crewstatus":null,"globalid":"{FFD66EA4-2EEC-4A80-9358-9CE320D72C83}","county":"POTTER","cause":"Outage","city":"Amarillo","xcelarea":"Amarillo"}},{"type":"Feature","id":182919,"geometry":{"type":"Point","coordinates":[-102.74615866003506,34.232646830076192]},"properties":{"objectid":182919,"boundary":null,"comments":"Crews are working to restore power as quickly and safely as possible. Please continue to check back for estimated restoration time updates. Thank you for your patience.","customers":1,"off_":1782360540000,"etr":null,"ticket":"25034831","outageimpact":"Small","outagetype":"Unplanned Outage","medialink":null,"outagestatus":0,"datastatus":null,"latlong":"4060083.7542999983,-11437650.063","states":"TX","crewstatus":null,"globalid":"{20CE82CA-D938-42C9-B543-B6AF9D9E2573}","county":"BAILEY","cause":"Outage","city":"Muleshoe","xcelarea":"Muleshoe"}},{"type":"Feature","id":182944,"geometry":{"type":"Point","coordinates":[-104.94851242982804,39.661256940064746]},"properties":{"objectid":182944,"boundary":null,"comments":"The outage has been reported. Please continue to check back for additional updates regarding the restoration progress.","customers":1,"off_":1782359220000,"etr":1782370800000,"ticket":"25034831","outageimpact":"Small","outagetype":"Unplanned Outage","medialink":null,"outagestatus":0,"datastatus":null,"latlong":"4816838.474799998,-11682814.9632","states":"CO","crewstatus":null,"globalid":"{0B882EFC-34F7-4C1A-9742-A9ACC6C70621}","county":"DENVER","cause":"Outage","city":"Denver","xcelarea":"Denver"}},{"type":"Feature","id":182817,"geometry":{"type":"Point","coordinates":[-105.11358920002391,39.82731574982072]},"properties":{"objectid":182817,"boundary":null,"comments":"The outage has been reported. Please continue to check back for additional updates regarding the restoration progress.","customers":11,"off_":1782345660000,"etr":1782360000000,"ticket":"25034831","outageimpact":"Small","outagetype":"Unplanned Outage","medialink":null,"outagestatus":0,"datastatus":null,"latlong":"4840879.9146,-11701191.225200001","states":"CO","crewstatus":null,"globalid":"{F966FA76-D26F-40DA-8F7A-0265F92D57A5}","county":"JEFFERSON","cause":"Outage","city":"Arvada","xcelarea":"Arvada"}},{"type":"Feature","id":182911,"geometry":{"type":"Point","coordinates":[-102.34687228005563,33.933701430047016]},"properties":{"objectid":182911,"boundary":null,"comments":"Crews are working to restore power as quickly and safely as possible. Please continue to check back for estimated restoration time updates. Thank you for your patience.","customers":4,"off_":1782340560000,"etr":1782362700000,"ticket":"25034831","outageimpact":"Small","outagetype":"Unplanned Outage","medialink":null,"outagestatus":0,"datastatus":null,"latlong":"4019903.2183,-11393201.7065","states":"TX","crewstatus":null,"globalid":"{B7D1D7D7-8AD4-4D84-9CC7-3D10484F51FC}","county":"LAMB","cause":"Outage","city":"Littlefield","xcelarea":"Littlefield"}},{"type":"Feature","id":182913,"geometry":{"type":"Point","coordinates":[-102.4160639197686,34.015949619759468]},"properties":{"objectid":182913,"boundary":null,"comments":"Crews are working to restore power as quickly and safely as possible. Please continue to check back for estimated restoration time updates. Thank you for your patience.","customers":1,"off_":1782342480000,"etr":null,"ticket":"25034831","outageimpact":"Small","outagetype":"Unplanned Outage","medialink":null,"outagestatus":0,"datastatus":null,"latlong":"4030943.8715000004,-11400904.0846","states":"TX","crewstatus":null,"globalid":"{BE3967C1-1CEC-4C42-AB17-790F174A0A7C}","county":"LAMB","cause":"Outage","city":"Amherst","xcelarea":"Amherst"}},{"type":"Feature","id":182916,"geometry":{"type":"Point","coordinates":[-102.7457676296801,34.233408259743499]},"properties":{"objectid":182916,"boundary":null,"comments":"Crews are working to restore power as quickly and safely as possible. Please continue to check back for estimated restoration time updates. Thank you for your patience.","customers":103,"off_":1782343800000,"etr":null,"ticket":"25034831","outageimpact":"Medium","outagetype":"Unplanned Outage","medialink":null,"outagestatus":0,"datastatus":null,"latlong":"4060186.277800001,-11437606.5337","states":"TX","crewstatus":null,"globalid":"{91F65B1E-4A64-4D0E-87A0-7B28893CD7B8}","county":"BAILEY","cause":"Outage","city":"Muleshoe","xcelarea":"Muleshoe"}},{"type":"Feature","id":182681,"geometry":{"type":"Point","coordinates":[-105.02653089036994,39.624192730065793]},"properties":{"objectid":182681,"boundary":null,"comments":"Crews are working to restore power as quickly and safely as possible. Please continue to check back for estimated restoration time updates. Thank you for your patience.","customers":24,"off_":1782338640000,"etr":1782360000000,"ticket":"25034831","outageimpact":"Small","outagetype":"Unplanned Outage","medialink":null,"outagestatus":0,"datastatus":null,"latlong":"4811480.335699998,-11691499.9385","states":"CO","crewstatus":null,"globalid":"{BFE40C2C-6E23-4B4C-B1AA-03B984EDD266}","county":"ARAPAHOE","cause":"Outage","city":"Englewood","xcelarea":"Englewood"}},{"type":"Feature","id":182923,"geometry":{"type":"Point","coordinates":[-101.97241558965082,34.985999350094552]},"properties":{"objectid":182923,"boundary":null,"comments":"Crews are working to restore power as quickly and safely as possible. Please continue to check back for estimated restoration time updates. Thank you for your patience.","customers":22,"off_":1782346260000,"etr":1782357300000,"ticket":"25034831","outageimpact":"Small","outagetype":"Unplanned Outage","medialink":null,"outagestatus":0,"datastatus":null,"latlong":"4161978.6744000018,-11351517.3784","states":"TX","crewstatus":null,"globalid":"{0F1DFB89-A370-4D89-AACA-9BD3812C555F}","county":"RANDALL","cause":"Outage","city":"Canyon","xcelarea":"Canyon"}},{"type":"Feature","id":182893,"geometry":{"type":"Point","coordinates":[-104.9830807203635,40.535029329830913]},"properties":{"objectid":182893,"boundary":null,"comments":"Crews are working to restore power as quickly and safely as possible. Please continue to check back for estimated restoration time updates. Thank you for your patience.","customers":1,"off_":1782352860000,"etr":1782360900000,"ticket":"25034831","outageimpact":"Small","outagetype":"Unplanned Outage","medialink":null,"outagestatus":0,"datastatus":null,"latlong":"4943998.627700001,-11686663.0877","states":"CO","crewstatus":null,"globalid":"{B1E4E313-4041-44B6-93F6-AC33060236EE}","county":"LARIMER","cause":"Outage","city":"Timnath","xcelarea":"Timnath"}},{"type":"Feature","id":182921,"geometry":{"type":"Point","coordinates":[-102.34578411032781,33.914189110364056]},"properties":{"objectid":182921,"boundary":null,"comments":"Crews are in the area working to restore power as quickly and safely as possible. Please continue to check back for estimated restoration time updates. Thank you for your patience.","customers":1,"off_":1782357120000,"etr":1782368100000,"ticket":"25034831","outageimpact":"Small","outagetype":"Unplanned Outage","medialink":null,"outagestatus":0,"datastatus":null,"latlong":"4017285.5319000036,-11393080.572","states":"TX","crewstatus":"Crew Onsite","globalid":"{AAC330FC-2496-4D7E-AC17-6DD170D94BF2}","county":"LAMB","cause":"Outage","city":"Littlefield","xcelarea":"Littlefield"}},{"type":"Feature","id":182922,"geometry":{"type":"Point","coordinates":[-102.32737630963273,33.915898140052775]},"properties":{"objectid":182922,"boundary":null,"comments":"Crews are working to restore power as quickly and safely as possible. Please continue to check back for estimated restoration time updates. Thank you for your patience.","customers":79,"off_":1782339780000,"etr":null,"ticket":"25034831","outageimpact":"Small","outagetype":"Unplanned Outage","medialink":null,"outagestatus":0,"datastatus":null,"latlong":"4017514.7837999985,-11391031.425","states":"TX","crewstatus":null,"globalid":"{EA4A8FE3-672C-488A-821F-FA460A6EB88C}","county":"LAMB","cause":"Outage","city":"Littlefield","xcelarea":"Littlefield"}},{"type":"Feature","id":182924,"geometry":{"type":"Point","coordinates":[-101.86703942042467,34.778533559975031]},"properties":{"objectid":182924,"boundary":null,"comments":"Crews are working to restore power as quickly and safely as possible. Please continue to check back for estimated restoration time updates. Thank you for your patience.","customers":2,"off_":1782347580000,"etr":null,"ticket":"25034831","outageimpact":"Small","outagetype":"Unplanned Outage","medialink":null,"outagestatus":0,"datastatus":null,"latlong":"4133825.319799997,-11339786.9569","states":"TX","crewstatus":null,"globalid":"{73D631DC-EBB0-438B-824D-24BF3CDD0B3F}","county":"RANDALL","cause":"Outage","city":"Happy","xcelarea":"Happy"}},{"type":"Feature","id":182886,"geometry":{"type":"Point","coordinates":[-104.9845946897394,39.675402659959687]},"properties":{"objectid":182886,"boundary":null,"comments":"The outage has been reported. Please continue to check back for additional updates regarding the restoration progress.","customers":1,"off_":1782351060000,"etr":1782359100000,"ticket":"25034831","outageimpact":"Small","outagetype":"Unplanned Outage","medialink":null,"outagestatus":0,"datastatus":null,"latlong":"4818884.189900003,-11686831.622000001","states":"CO","crewstatus":null,"globalid":"{82AC85C4-3906-4E93-BDE9-E12F88E4D946}","county":"DENVER","cause":"Outage","city":"Denver","xcelarea":"Denver"}},{"type":"Feature","id":182788,"geometry":{"type":"Point","coordinates":[-105.14359501011337,39.754657849962243]},"properties":{"objectid":182788,"boundary":null,"comments":"The outage has been reported. Please continue to check back for additional updates regarding the restoration progress.","customers":48,"off_":1782344460000,"etr":1782358200000,"ticket":"25034831","outageimpact":"Small","outagetype":"Unplanned Outage","medialink":null,"outagestatus":0,"datastatus":null,"latlong":"4830353.615900002,-11704531.4567","states":"CO","crewstatus":null,"globalid":"{1ADA7ACA-8005-4AD7-8046-CB366E7299BB}","county":"JEFFERSON","cause":"Outage","city":"Golden","xcelarea":"Golden"}},{"type":"Feature","id":182929,"geometry":{"type":"Point","coordinates":[-102.30130521031923,33.903254800060466]},"properties":{"objectid":182929,"boundary":null,"comments":"Crews are working to restore power as quickly and safely as possible. Please continue to check back for estimated restoration time updates. Thank you for your patience.","customers":2,"off_":1782356460000,"etr":1782368100000,"ticket":"25034831","outageimpact":"Small","outagetype":"Unplanned Outage","medialink":null,"outagestatus":0,"datastatus":null,"latlong":"4015818.895300001,-11388129.2035","states":"TX","crewstatus":null,"globalid":"{12ADA6C2-D76A-4DC8-A468-F5770C454120}","county":"LAMB","cause":"Outage","city":"Littlefield","xcelarea":"Littlefield"}},{"type":"Feature","id":182938,"geometry":{"type":"Point","coordinates":[-102.33217182024991,33.917994530099811]},"properties":{"objectid":182938,"boundary":null,"comments":"Crews are working to restore power as quickly and safely as possible. Please continue to check back for estimated restoration time updates. Thank you for your patience.","customers":1,"off_":1782360720000,"etr":null,"ticket":"25034831","outageimpact":"Small","outagetype":"Unplanned Outage","medialink":null,"outagestatus":0,"datastatus":null,"latlong":"4017796.0031000003,-11391565.2588","states":"TX","crewstatus":null,"globalid":"{EEB5E98A-9891-4B5A-8E77-690AF7A7EA49}","county":"LAMB","cause":"Outage","city":"Littlefield","xcelarea":"Littlefield"}},{"type":"Feature","id":182877,"geometry":{"type":"Point","coordinates":[-105.00827910009026,39.654914699663195]},"properties":{"objectid":182877,"boundary":null,"comments":"The outage has been reported. Please continue to check back for additional updates regarding the restoration progress.","customers":1,"off_":1782349500000,"etr":1782357300000,"ticket":"25034831","outageimpact":"Small","outagetype":"Unplanned Outage","medialink":null,"outagestatus":0,"datastatus":null,"latlong":"4815921.413400002,-11689468.1585","states":"CO","crewstatus":null,"globalid":"{D775BF11-6024-4AAD-9B31-B164B1574C3F}","county":"ARAPAHOE","cause":"Outage","city":"Sheridan","xcelarea":"Sheridan"}},{"type":"Feature","id":182694,"geometry":{"type":"Point","coordinates":[-105.03847604023117,39.623655910001219]},"properties":{"objectid":182694,"boundary":null,"comments":"Crews are working to restore power as quickly and safely as possible. Please continue to check back for estimated restoration time updates. Thank you for your patience.","customers":20,"off_":1782338340000,"etr":1782360000000,"ticket":"25034831","outageimpact":"Small","outagetype":"Unplanned Outage","medialink":null,"outagestatus":0,"datastatus":null,"latlong":"4811402.752099998,-11692829.6665","states":"CO","crewstatus":null,"globalid":"{15563565-6D08-4DE2-93EB-296B7CF48C14}","county":"ARAPAHOE","cause":"Outage","city":"Littleton","xcelarea":"Littleton"}},{"type":"Feature","id":182443,"geometry":{"type":"Point","coordinates":[-103.37185389995804,40.471850339918802]},"properties":{"objectid":182443,"boundary":null,"comments":"Crews are working to restore power as quickly and safely as possible. Please continue to check back for estimated restoration time updates. Thank you for your patience.","customers":9,"off_":1782318240000,"etr":1782345600000,"ticket":"25034831","outageimpact":"Small","outagetype":"Unplanned Outage","medialink":null,"outagestatus":0,"datastatus":null,"latlong":"4934749.0757,-11507302.1385","states":"CO","crewstatus":null,"globalid":"{A71E0BF5-0751-4664-BD14-A8C673C770CF}","county":"LOGAN","cause":"Outage","city":"Merino","xcelarea":"Merino"}},{"type":"Feature","id":182928,"geometry":{"type":"Point","coordinates":[-93.310990019617023,44.806164670017758]},"properties":{"objectid":182928,"boundary":null,"comments":"Crews are working to restore power as quickly and safely as possible. Please continue to check back for estimated restoration time updates. Thank you for your patience.","customers":1,"off_":1782359880000,"etr":1782369900000,"ticket":"25034831","outageimpact":"Small","outagetype":"Unplanned Outage","medialink":null,"outagestatus":0,"datastatus":null,"latlong":"5591057.524300002,-10387331.8944","states":"MN","crewstatus":null,"globalid":"{01EB5140-5D82-4897-BB8B-E1BFFF1E4D87}","county":"HENNEPIN","cause":"Outage","city":"Bloomington","xcelarea":"Bloomington"}},{"type":"Feature","id":182925,"geometry":{"type":"Point","coordinates":[-102.34696131028683,33.93248425016214]},"properties":{"objectid":182925,"boundary":null,"comments":"Crews are working to restore power as quickly and safely as possible. Please continue to check back for estimated restoration time updates. Thank you for your patience.","customers":1,"off_":1782349260000,"etr":null,"ticket":"25034831","outageimpact":"Small","outagetype":"Unplanned Outage","medialink":null,"outagestatus":0,"datastatus":null,"latlong":"4019739.9092999995,-11393211.6173","states":"TX","crewstatus":null,"globalid":"{2A6E8EB1-95BD-4452-B995-DEE05216A5AF}","county":"LAMB","cause":"Outage","city":"Littlefield","xcelarea":"Littlefield"}},{"type":"Feature","id":182926,"geometry":{"type":"Point","coordinates":[-101.55624608986363,35.246849779801785]},"properties":{"objectid":182926,"boundary":null,"comments":"Crews are working to restore power as quickly and safely as possible. Please continue to check back for estimated restoration time updates. Thank you for your patience.","customers":1,"off_":1782353460000,"etr":null,"ticket":"25034831","outageimpact":"Small","outagetype":"Unplanned Outage","medialink":null,"outagestatus":0,"datastatus":null,"latlong":"4197477.8488000035,-11305189.6016","states":"TX","crewstatus":null,"globalid":"{2AA00246-0F15-4781-AA0B-26EA9CC67F8F}","county":"CARSON","cause":"Outage","city":"Panhandle","xcelarea":"Panhandle"}},{"type":"Feature","id":182930,"geometry":{"type":"Point","coordinates":[-92.378670719911142,44.935025820031193]},"properties":{"objectid":182930,"boundary":null,"comments":"Crews are working to restore power as quickly and safely as possible. Please continue to check back for estimated restoration time updates. Thank you for your patience.","customers":2,"off_":1782335820000,"etr":1782345600000,"ticket":"25034831","outageimpact":"Small","outagetype":"Unplanned Outage","medialink":null,"outagestatus":0,"datastatus":null,"latlong":"5611298.424599998,-10283546.5847","states":"WI","crewstatus":null,"globalid":"{7D9CE2EF-0432-4337-8042-B885F2F0EDDB}","county":"ST CROIX","cause":"Outage","city":"Baldwin","xcelarea":"Baldwin"}},{"type":"Feature","id":182931,"geometry":{"type":"Point","coordinates":[-101.39824259043455,35.330283359899539]},"properties":{"objectid":182931,"boundary":null,"comments":"Crews are in the area working to restore power as quickly and safely as possible. Please continue to check back for estimated restoration time updates. Thank you for your patience.","customers":53,"off_":1782349680000,"etr":1782361800000,"ticket":"25034831","outageimpact":"Small","outagetype":"Unplanned Outage","medialink":null,"outagestatus":0,"datastatus":null,"latlong":"4208856.412299998,-11287600.7325","states":"TX","crewstatus":"Crew Onsite","globalid":"{6AF33DAD-981A-48AC-AE31-85DD138EB1A0}","county":"CARSON","cause":"Outage","city":"Panhandle","xcelarea":"Panhandle"}},{"type":"Feature","id":182934,"geometry":{"type":"Point","coordinates":[-102.3194231597064,33.926671630307126]},"properties":{"objectid":182934,"boundary":null,"comments":"Crews are working to restore power as quickly and safely as possible. Please continue to check back for estimated restoration time updates. Thank you for your patience.","customers":1,"off_":1782343740000,"etr":null,"ticket":"25034831","outageimpact":"Small","outagetype":"Unplanned Outage","medialink":null,"outagestatus":0,"datastatus":null,"latlong":"4018960.0623999983,-11390146.0844","states":"TX","crewstatus":null,"globalid":"{DD77AE8A-C119-4B95-8068-0FE4E16E01D1}","county":"LAMB","cause":"Outage","city":"Littlefield","xcelarea":"Littlefield"}},{"type":"Feature","id":182852,"geometry":{"type":"Point","coordinates":[-105.07678097020896,39.763230399730098]},"properties":{"objectid":182852,"boundary":null,"comments":"Crews are working to restore power as quickly and safely as possible. Please continue to check back for estimated restoration time updates. Thank you for your patience.","customers":1,"off_":1782347580000,"etr":1782360000000,"ticket":"25034831","outageimpact":"Small","outagetype":"Unplanned Outage","medialink":null,"outagestatus":0,"datastatus":null,"latlong":"4831594.984099999,-11697093.7518","states":"CO","crewstatus":null,"globalid":"{11A5F083-EB0B-4D8A-88E0-D49527504712}","county":"JEFFERSON","cause":"Outage","city":"Wheat Ridge","xcelarea":"Wheat Ridge"}},{"type":"Feature","id":181029,"geometry":{"type":"Point","coordinates":[-107.76659763004311,39.518951649718275]},"properties":{"objectid":181029,"boundary":null,"comments":"Crews are working to restore power as quickly and safely as possible. Please continue to check back for estimated restoration time updates. Thank you for your patience.","customers":86,"off_":1782228660000,"etr":1782381600000,"ticket":"25034831","outageimpact":"Small","outagetype":"Unplanned Outage","medialink":null,"outagestatus":0,"datastatus":null,"latlong":"4796281.917999998,-11996522.7727","states":"CO","crewstatus":null,"globalid":"{6D38BDFB-96D6-40AE-AF12-61D1FED89519}","county":"GARFIELD","cause":"Outage","city":"Rifle","xcelarea":"Rifle"}},{"type":"Feature","id":181070,"geometry":{"type":"Point","coordinates":[-107.74308691973216,39.523742990250057]},"properties":{"objectid":181070,"boundary":null,"comments":"Crews are working to restore power as quickly and safely as possible. Please continue to check back for estimated restoration time updates. Thank you for your patience.","customers":19,"off_":1782230880000,"etr":1782381600000,"ticket":"25034831","outageimpact":"Small","outagetype":"Unplanned Outage","medialink":null,"outagestatus":0,"datastatus":null,"latlong":"4796973.3598000035,-11993905.5724","states":"CO","crewstatus":null,"globalid":"{5C334C50-6094-4DB8-AB7A-0E461042B9FE}","county":"GARFIELD","cause":"Outage","city":"Silt,  Rifle","xcelarea":"Silt,  Rifle"}},{"type":"Feature","id":182870,"geometry":{"type":"Point","coordinates":[-104.99010913016329,39.648334699757932]},"properties":{"objectid":182870,"boundary":null,"comments":"Crews are working to restore power as quickly and safely as possible. Please continue to check back for estimated restoration time updates. Thank you for your patience.","customers":810,"off_":1782338460000,"etr":1782360000000,"ticket":"25034831","outageimpact":"Medium","outagetype":"Unplanned Outage","medialink":null,"outagestatus":0,"datastatus":null,"latlong":"4814970.061899997,-11687445.4867","states":"CO","crewstatus":null,"globalid":"{BAE89FBF-5748-42B3-AD17-CC9035D38A22}","county":"ARAPAHOE","cause":"Outage","city":"Englewood","xcelarea":"Englewood"}},{"type":"Feature","id":182695,"geometry":{"type":"Point","coordinates":[-105.03690093960189,39.617130000206572]},"properties":{"objectid":182695,"boundary":null,"comments":"The outage has been reported. Please continue to check back for additional updates regarding the restoration progress.","customers":20,"off_":1782338520000,"etr":1782358200000,"ticket":"25034831","outageimpact":"Small","outagetype":"Unplanned Outage","medialink":null,"outagestatus":0,"datastatus":null,"latlong":"4810459.647,-11692654.327100001","states":"CO","crewstatus":null,"globalid":"{B24BE910-77FD-449C-B5EE-EFCB38ECB832}","county":"ARAPAHOE","cause":"Outage","city":"Littleton","xcelarea":"Littleton"}},{"type":"Feature","id":182533,"geometry":{"type":"Point","coordinates":[-103.17606426020417,32.690872089982349]},"properties":{"objectid":182533,"boundary":null,"comments":"Crews are working to restore power as quickly and safely as possible. Please continue to check back for estimated restoration time updates. Thank you for your patience.","customers":1,"off_":1782337440000,"etr":null,"ticket":"25034831","outageimpact":"Small","outagetype":"Unplanned Outage","medialink":null,"outagestatus":0,"datastatus":null,"latlong":"3854343.9201000035,-11485506.9355","states":"NM","crewstatus":null,"globalid":"{4D6419FC-5F3C-49AF-8725-DA11A73444E3}","county":"LEA-OUT","cause":"Outage","city":"Hobbs","xcelarea":"Hobbs"}},{"type":"Feature","id":181893,"geometry":{"type":"Point","coordinates":[-105.00308722043036,39.764169330052262]},"properties":{"objectid":181893,"boundary":null,"comments":"Crews are working to restore power as quickly and safely as possible. Please continue to check back for estimated restoration time updates. Thank you for your patience.","customers":28,"off_":1782294060000,"etr":1782360000000,"ticket":"25034831","outageimpact":"Small","outagetype":"Unplanned Outage","medialink":null,"outagestatus":0,"datastatus":null,"latlong":"4831730.957500003,-11688890.2011","states":"CO","crewstatus":null,"globalid":"{B707AC60-7415-45B7-8ECD-5187D276763F}","county":"DENVER","cause":"Outage","city":"Denver","xcelarea":"Denver"}},{"type":"Feature","id":182710,"geometry":{"type":"Point","coordinates":[-105.00885370027522,39.620722270292468]},"properties":{"objectid":182710,"boundary":null,"comments":"Crews are working to restore power as quickly and safely as possible. Please continue to check back for estimated restoration time updates. Thank you for your patience.","customers":26,"off_":1782338820000,"etr":1782360000000,"ticket":"25034831","outageimpact":"Small","outagetype":"Unplanned Outage","medialink":null,"outagestatus":0,"datastatus":null,"latlong":"4810978.780199997,-11689532.1227","states":"CO","crewstatus":null,"globalid":"{5F2BEAF4-F35E-4E5C-ABF9-6DE24548F0F3}","county":"ARAPAHOE","cause":"Outage","city":"Littleton","xcelarea":"Littleton"}},{"type":"Feature","id":182498,"geometry":{"type":"Point","coordinates":[-105.07871136980448,39.792880619781286]},"properties":{"objectid":182498,"boundary":null,"comments":"The outage has been reported. Please continue to check back for additional updates regarding the restoration progress.","customers":8,"off_":1782335340000,"etr":1782358200000,"ticket":"25034831","outageimpact":"Small","outagetype":"Unplanned Outage","medialink":null,"outagestatus":0,"datastatus":null,"latlong":"4835889.745999999,-11697308.642900001","states":"CO","crewstatus":null,"globalid":"{02CB0182-0F1E-44D9-95FF-EF7F124EF24B}","county":"JEFFERSON","cause":"Outage","city":"Arvada","xcelarea":"Arvada"}}]}