{"type":"FeatureCollection","features":[{"type":"Feature","id":66183,"geometry":{"type":"Point","coordinates":[-90.112949199783245,44.888030939859469]},"properties":{"objectid":66183,"boundary":null,"comments":"Crews are working to restore power as quickly and safely as possible. Please continue to check back for estimated restoration time updates. Thank you for your patience.","customers":2,"off_":1769157900000,"etr":1769163300000,"ticket":"23092932","outageimpact":"Small","outagetype":"Unplanned Outage","medialink":null,"outagestatus":0,"datastatus":null,"latlong":"5603911.439499997,-10031327.6188","states":"WI","crewstatus":null,"globalid":"{B3CD3F38-FAF5-4F2E-80A6-711968DEFCB2}","county":"MARATHON","cause":"Outage","city":"Edgar","xcelarea":"Edgar"}},{"type":"Feature","id":66170,"geometry":{"type":"Point","coordinates":[-101.33054444030562,33.143172880307382]},"properties":{"objectid":66170,"boundary":null,"comments":"Crews are working to restore power as quickly and safely as possible. Please continue to check back for estimated restoration time updates. Thank you for your patience.","customers":1,"off_":1769155800000,"etr":1769166900000,"ticket":"23092932","outageimpact":"Small","outagetype":"Unplanned Outage","medialink":null,"outagestatus":0,"datastatus":null,"latlong":"3914323.2245000005,-11280064.6089","states":"TX","crewstatus":null,"globalid":"{9E4FD610-3AD4-46B1-99AD-A7551F8CC496}","county":"GARZA","cause":"Outage","city":"Post","xcelarea":"Post"}},{"type":"Feature","id":66179,"geometry":{"type":"Point","coordinates":[-93.809425340373565,44.853649420277932]},"properties":{"objectid":66179,"boundary":null,"comments":"Crews are in the area working to restore power as quickly and safely as possible. Please continue to check back for estimated restoration time updates. Thank you for your patience.","customers":1,"off_":1769157120000,"etr":1769164200000,"ticket":"23092932","outageimpact":"Small","outagetype":"Unplanned Outage","medialink":null,"outagestatus":0,"datastatus":null,"latlong":"5598510.9331,-10442817.4605","states":"MN","crewstatus":"Crew Onsite","globalid":"{42A944EA-B703-49CA-B741-7A77D72CD347}","county":"CARVER","cause":"Outage","city":"Waconia","xcelarea":"Waconia"}},{"type":"Feature","id":66176,"geometry":{"type":"Point","coordinates":[-93.762173470440317,44.90245837001865]},"properties":{"objectid":66176,"boundary":null,"comments":"Crews are working to restore power as quickly and safely as possible. Please continue to check back for estimated restoration time updates. Thank you for your patience.","customers":1,"off_":1769156340000,"etr":1769162400000,"ticket":"23092932","outageimpact":"Small","outagetype":"Unplanned Outage","medialink":null,"outagestatus":0,"datastatus":null,"latlong":"5606178.601800002,-10437557.4064","states":"MN","crewstatus":null,"globalid":"{F243CD53-B5B7-4C0D-B612-3A60F5AEB252}","county":"HENNEPIN","cause":"Outage","city":"Minnetrista","xcelarea":"Minnetrista"}},{"type":"Feature","id":66182,"geometry":{"type":"Point","coordinates":[-90.093942140148641,44.881138239891314]},"properties":{"objectid":66182,"boundary":null,"comments":"Crews are working to restore power as quickly and safely as possible. Please continue to check back for estimated restoration time updates. Thank you for your patience.","customers":2,"off_":1769157660000,"etr":1769163300000,"ticket":"23092932","outageimpact":"Small","outagetype":"Unplanned Outage","medialink":null,"outagestatus":0,"datastatus":null,"latlong":"5602828.504199997,-10029211.7626","states":"WI","crewstatus":null,"globalid":"{2A93D68F-211C-434E-AE95-E01483D7C568}","county":"MARATHON","cause":"Outage","city":"Edgar","xcelarea":"Edgar"}},{"type":"Feature","id":66199,"geometry":{"type":"Point","coordinates":[-101.33795106958611,33.9894579596277]},"properties":{"objectid":66199,"boundary":null,"comments":"Crews are in the area working to restore power as quickly and safely as possible. Please continue to check back for estimated restoration time updates. Thank you for your patience.","customers":2,"off_":1769161800000,"etr":1769176800000,"ticket":"23092932","outageimpact":"Small","outagetype":"Unplanned Outage","medialink":null,"outagestatus":0,"datastatus":null,"latlong":"4027386.5754999965,-11280889.1111","states":"TX","crewstatus":"Crew Onsite","globalid":"{6F048260-21E2-4BB9-815A-0BCDB055E4A2}","county":"FLOYD","cause":"Outage","city":"Floydada","xcelarea":"Floydada"}},{"type":"Feature","id":66193,"geometry":{"type":"Point","coordinates":[-104.7360621299617,40.428174169728145]},"properties":{"objectid":66193,"boundary":null,"comments":"Crews are working to restore power as quickly and safely as possible. Please continue to check back for estimated restoration time updates. Thank you for your patience.","customers":12,"off_":1769156700000,"etr":1769185800000,"ticket":"23092932","outageimpact":"Small","outagetype":"Unplanned Outage","medialink":null,"outagestatus":0,"datastatus":null,"latlong":"4928359.868900001,-11659165.104","states":"CO","crewstatus":null,"globalid":"{4904E369-BA28-4ADB-AA97-FF9DE68F839A}","county":"WELD","cause":"Outage","city":"Greeley","xcelarea":"Greeley"}},{"type":"Feature","id":66146,"geometry":{"type":"Point","coordinates":[-92.961030120210495,44.833179250076398]},"properties":{"objectid":66146,"boundary":null,"comments":"Crews are in the area working to restore power as quickly and safely as possible. Please continue to check back for estimated restoration time updates. Thank you for your patience.","customers":21,"off_":1769152380000,"etr":1769167800000,"ticket":"23092932","outageimpact":"Small","outagetype":"Unplanned Outage","medialink":null,"outagestatus":0,"datastatus":null,"latlong":"5595297.094899997,-10348374.5366","states":"MN","crewstatus":"Crew Onsite","globalid":"{30A2FA74-7DFB-41EC-8510-550B2AA1A11A}","county":"WASHINGTON","cause":"Outage","city":"Cottage Grove","xcelarea":"Cottage Grove"}},{"type":"Feature","id":66230,"geometry":{"type":"Point","coordinates":[-104.96846315978713,39.739445039860364]},"properties":{"objectid":66230,"boundary":null,"comments":"The outage has been reported. Please continue to check back for additional updates regarding the restoration progress.","customers":1,"off_":1769160060000,"etr":1769171400000,"ticket":"23092932","outageimpact":"Small","outagetype":"Unplanned Outage","medialink":null,"outagestatus":0,"datastatus":null,"latlong":"4828151.069499999,-11685035.8683","states":"CO","crewstatus":null,"globalid":"{8727A4F2-D04C-48BD-8C7D-2E2C53703E23}","county":"DENVER","cause":"Outage","city":"Denver","xcelarea":"Denver"}},{"type":"Feature","id":66231,"geometry":{"type":"Point","coordinates":[-93.084664170293948,44.985157119950166]},"properties":{"objectid":66231,"boundary":null,"comments":"The outage has been reported. Please continue to check back for additional updates regarding the restoration progress.","customers":1,"off_":1769163780000,"etr":1769175000000,"ticket":"23092932","outageimpact":"Small","outagetype":"Unplanned Outage","medialink":null,"outagestatus":0,"datastatus":null,"latlong":"5619185.081100002,-10362137.4161","states":"MN","crewstatus":null,"globalid":"{F1988DA4-BA88-480F-9E4C-D97AC295835D}","county":"RAMSEY","cause":"Outage","city":"Saint Paul","xcelarea":"Saint Paul"}},{"type":"Feature","id":66180,"geometry":{"type":"Point","coordinates":[-93.352414489556111,44.944373610162948]},"properties":{"objectid":66180,"boundary":null,"comments":"Crews are in the area working to restore power as quickly and safely as possible. Please continue to check back for estimated restoration time updates. Thank you for your patience.","customers":1,"off_":1769157360000,"etr":1769169600000,"ticket":"23092932","outageimpact":"Small","outagetype":"Unplanned Outage","medialink":null,"outagestatus":0,"datastatus":null,"latlong":"5612768.4965,-10391943.2453","states":"MN","crewstatus":"Crew Onsite","globalid":"{BDEDB68E-1E33-4ABC-97E5-5D55C28400FB}","county":"HENNEPIN","cause":"Outage","city":"Saint Louis Park","xcelarea":"Saint Louis Park"}},{"type":"Feature","id":66130,"geometry":{"type":"Point","coordinates":[-93.755701520246632,44.895597640184484]},"properties":{"objectid":66130,"boundary":null,"comments":"Crews are working to restore power as quickly and safely as possible. Please continue to check back for estimated restoration time updates. Thank you for your patience.","customers":1,"off_":1769149140000,"etr":1769157000000,"ticket":"23092932","outageimpact":"Small","outagetype":"Unplanned Outage","medialink":null,"outagestatus":0,"datastatus":null,"latlong":"5605100.418700002,-10436836.9522","states":"MN","crewstatus":null,"globalid":"{B8D2BD1F-4676-4C11-9D8B-86543DE9A528}","county":"HENNEPIN","cause":"Outage","city":"Minnetrista","xcelarea":"Minnetrista"}},{"type":"Feature","id":66131,"geometry":{"type":"Point","coordinates":[-93.747161519809822,44.900422219746162]},"properties":{"objectid":66131,"boundary":null,"comments":"Crews are in the area working to restore power as quickly and safely as possible. Please continue to check back for estimated restoration time updates. Thank you for your patience.","customers":165,"off_":1769149140000,"etr":1769158800000,"ticket":"23092932","outageimpact":"Medium","outagetype":"Unplanned Outage","medialink":null,"outagestatus":0,"datastatus":null,"latlong":"5605858.601599999,-10435886.2837","states":"MN","crewstatus":"Crew Onsite","globalid":"{BCC98400-AE2A-4230-B88F-80B075535D77}","county":"HENNEPIN","cause":"Outage","city":"Waconia,  Saint Bonifacius,  Minnetrista","xcelarea":"Waconia,  Saint Bonifacius,  Minnetrista"}},{"type":"Feature","id":66217,"geometry":{"type":"Point","coordinates":[-93.284075999631412,44.297792910104739]},"properties":{"objectid":66217,"boundary":null,"comments":"Crews are working to restore power as quickly and safely as possible. Please continue to check back for estimated restoration time updates. Thank you for your patience.","customers":1,"off_":1769163120000,"etr":1769168700000,"ticket":"23092932","outageimpact":"Small","outagetype":"Unplanned Outage","medialink":null,"outagestatus":0,"datastatus":null,"latlong":"5511642.570500001,-10384335.8394","states":"MN","crewstatus":null,"globalid":"{78AC1391-1508-4993-ADA4-D0F5005CED62}","county":"RICE","cause":"Outage","city":"Faribault","xcelarea":"Faribault"}},{"type":"Feature","id":66221,"geometry":{"type":"Point","coordinates":[-92.954268430100029,45.25832260024174]},"properties":{"objectid":66221,"boundary":null,"comments":"Crews are in the area working to restore power as quickly and safely as possible. Please continue to check back for estimated restoration time updates. Thank you for your patience.","customers":1,"off_":1769163300000,"etr":1769169600000,"ticket":"23092932","outageimpact":"Small","outagetype":"Unplanned Outage","medialink":null,"outagestatus":0,"datastatus":null,"latlong":"5662281.184299998,-10347621.8287","states":"MN","crewstatus":"Crew Onsite","globalid":"{78A22130-A035-425E-9055-95597EEEC084}","county":"WASHINGTON","cause":"Outage","city":"Forest Lake","xcelarea":"Forest Lake"}},{"type":"Feature","id":66223,"geometry":{"type":"Point","coordinates":[-93.179464479968374,44.914797200200255]},"properties":{"objectid":66223,"boundary":null,"comments":"Crews are working to restore power as quickly and safely as possible. Please continue to check back for estimated restoration time updates. Thank you for your patience.","customers":1,"off_":1769163360000,"etr":1769169600000,"ticket":"23092932","outageimpact":"Small","outagetype":"Unplanned Outage","medialink":null,"outagestatus":0,"datastatus":null,"latlong":"5608118.007700004,-10372690.5383","states":"MN","crewstatus":null,"globalid":"{38AFC8C5-4258-499F-B0BF-CE90033B03E6}","county":"RAMSEY","cause":"Outage","city":"Saint Paul","xcelarea":"Saint Paul"}},{"type":"Feature","id":66224,"geometry":{"type":"Point","coordinates":[-93.959746729563861,44.232141689975847]},"properties":{"objectid":66224,"boundary":null,"comments":"The outage has been reported. Please continue to check back for additional updates regarding the restoration progress.","customers":1,"off_":1769163360000,"etr":1769168700000,"ticket":"23092932","outageimpact":"Small","outagetype":"Unplanned Outage","medialink":null,"outagestatus":0,"datastatus":null,"latlong":"5501437.206500001,-10459551.161","states":"MN","crewstatus":null,"globalid":"{1524283E-8C43-4D8C-A6CE-5E14656F9D16}","county":"BLUE EARTH","cause":"Outage","city":"Mankato","xcelarea":"Mankato"}},{"type":"Feature","id":66206,"geometry":{"type":"Point","coordinates":[-105.10670263959734,39.984618499787729]},"properties":{"objectid":66206,"boundary":null,"comments":"Crews are working to restore power as quickly and safely as possible. Please continue to check back for estimated restoration time updates. Thank you for your patience.","customers":34,"off_":1769158440000,"etr":1769167800000,"ticket":"23092932","outageimpact":"Small","outagetype":"Unplanned Outage","medialink":null,"outagestatus":0,"datastatus":null,"latlong":"4863707.333499998,-11700424.616799999","states":"CO","crewstatus":null,"globalid":"{42B0DD0A-8F31-4380-AD94-A24721FDC995}","county":"BOULDER","cause":"Outage","city":"Lafayette","xcelarea":"Lafayette"}},{"type":"Feature","id":66229,"geometry":{"type":"Point","coordinates":[-93.354406790261223,45.014541939874995]},"properties":{"objectid":66229,"boundary":null,"comments":"The outage has been reported. Please continue to check back for additional updates regarding the restoration progress.","customers":1,"off_":1769163420000,"etr":1769169600000,"ticket":"23092932","outageimpact":"Small","outagetype":"Unplanned Outage","medialink":null,"outagestatus":0,"datastatus":null,"latlong":"5623811.1076000035,-10392165.0272","states":"MN","crewstatus":null,"globalid":"{BD3F7270-5A45-4D1F-B9A1-930020A04E8C}","county":"HENNEPIN","cause":"Outage","city":"Crystal","xcelarea":"Crystal"}}]}