{"type":"FeatureCollection","features":[{"type":"Feature","id":52353,"geometry":{"type":"Point","coordinates":[-105.29028415038552,40.045563530147014]},"properties":{"objectid":52353,"boundary":null,"comments":"The outage has been reported. Please continue to check back for additional updates regarding the restoration progress.","customers":1,"off_":1766834700000,"etr":1766842200000,"ticket":"27121335","outageimpact":"Small","outagetype":"Unplanned Outage","medialink":null,"outagestatus":0,"datastatus":null,"latlong":"4872565.658299997,-11720860.8171","states":"CO","crewstatus":null,"globalid":"{D9F979E6-C2AE-4E1A-9348-BD632CE77685}","county":"BOULDER","cause":"Outage","city":"Boulder","xcelarea":"Boulder"}},{"type":"Feature","id":52357,"geometry":{"type":"Point","coordinates":[-100.75883900986858,35.851893279973005]},"properties":{"objectid":52357,"boundary":null,"comments":"Crews are working to restore power as quickly and safely as possible. Please continue to check back for estimated restoration time updates. Thank you for your patience.","customers":2,"off_":1766839200000,"etr":1766844900000,"ticket":"27121335","outageimpact":"Small","outagetype":"Unplanned Outage","medialink":null,"outagestatus":0,"datastatus":null,"latlong":"4280261.206100002,-11216422.6515","states":"TX","crewstatus":null,"globalid":"{E927F585-311E-44B1-8938-1BFD08D9591E}","county":"ROBERTS","cause":"Outage","city":"Miami","xcelarea":"Miami"}},{"type":"Feature","id":52354,"geometry":{"type":"Point","coordinates":[-105.11197929955883,39.696792269781582]},"properties":{"objectid":52354,"boundary":null,"comments":"Crews are in the area working to restore power as quickly and safely as possible. Please continue to check back for estimated restoration time updates. Thank you for your patience.","customers":105,"off_":1766834580000,"etr":1766840400000,"ticket":"27121335","outageimpact":"Medium","outagetype":"Unplanned Outage","medialink":null,"outagestatus":0,"datastatus":null,"latlong":"4821978.292300001,-11701012.0119","states":"CO","crewstatus":"Crew Onsite","globalid":"{C2E02F6B-4D21-42DC-8BBB-086D43283D1C}","county":"JEFFERSON","cause":"Outage","city":"Lakewood","xcelarea":"Lakewood"}},{"type":"Feature","id":52331,"geometry":{"type":"Point","coordinates":[-93.517544069910883,44.994149579886901]},"properties":{"objectid":52331,"boundary":null,"comments":"Crews are in the area working to restore power as quickly and safely as possible. Please continue to check back for estimated restoration time updates. Thank you for your patience.","customers":13,"off_":1766835000000,"etr":1766843100000,"ticket":"27121335","outageimpact":"Small","outagetype":"Unplanned Outage","medialink":null,"outagestatus":0,"datastatus":null,"latlong":"5620600.504299998,-10410325.3861","states":"MN","crewstatus":"Crew Onsite","globalid":"{477BD496-DD7B-4FE0-AE37-730326035E6D}","county":"HENNEPIN","cause":"Outage","city":"Plymouth","xcelarea":"Plymouth"}},{"type":"Feature","id":52364,"geometry":{"type":"Point","coordinates":[-105.01218579959905,39.70401274029777]},"properties":{"objectid":52364,"boundary":null,"comments":"Crews are working to restore power as quickly and safely as possible. Please continue to check back for estimated restoration time updates. Thank you for your patience.","customers":168,"off_":1766836920000,"etr":1766848500000,"ticket":"27121335","outageimpact":"Medium","outagetype":"Unplanned Outage","medialink":null,"outagestatus":0,"datastatus":null,"latlong":"4823022.982000001,-11689903.0503","states":"CO","crewstatus":null,"globalid":"{B3A4B969-A9B6-4D6A-B8E5-758AA441FF7C}","county":"DENVER","cause":"Outage","city":"Denver","xcelarea":"Denver"}},{"type":"Feature","id":52245,"geometry":{"type":"Point","coordinates":[-93.165136060132497,44.44759457993527]},"properties":{"objectid":52245,"boundary":null,"comments":"Crews are in the area working to restore power as quickly and safely as possible. Please continue to check back for estimated restoration time updates. Thank you for your patience.","customers":1,"off_":1766829720000,"etr":1766846700000,"ticket":"27121335","outageimpact":"Small","outagetype":"Unplanned Outage","medialink":null,"outagestatus":0,"datastatus":null,"latlong":"5534971.779200003,-10371095.5059","states":"MN","crewstatus":"Crew Onsite","globalid":"{D4326E18-3504-4493-9F45-C725EEB55B99}","county":"RICE","cause":"Outage","city":"Northfield","xcelarea":"Northfield"}},{"type":"Feature","id":52328,"geometry":{"type":"Point","coordinates":[-104.53341206985773,33.388044150312851]},"properties":{"objectid":52328,"boundary":null,"comments":"Crews are in the area working to restore power as quickly and safely as possible. Please continue to check back for estimated restoration time updates. Thank you for your patience.","customers":1,"off_":1766831640000,"etr":1766843100000,"ticket":"27121335","outageimpact":"Small","outagetype":"Unplanned Outage","medialink":null,"outagestatus":0,"datastatus":null,"latlong":"3946924.3312000036,-11636606.2025","states":"NM","crewstatus":"Crew Onsite","globalid":"{21578368-2BE5-4B60-B32C-DDF28CAFD535}","county":"CHAVES-IN","cause":"Outage","city":"Roswell","xcelarea":"Roswell"}},{"type":"Feature","id":52365,"geometry":{"type":"Point","coordinates":[-105.10443780979796,40.121442460121898]},"properties":{"objectid":52365,"boundary":null,"comments":"The outage has been reported. Please continue to check back for additional updates regarding the restoration progress.","customers":1,"off_":1766836920000,"etr":1766848500000,"ticket":"27121335","outageimpact":"Small","outagetype":"Unplanned Outage","medialink":null,"outagestatus":0,"datastatus":null,"latlong":"4883605.692199998,-11700172.4971","states":"CO","crewstatus":null,"globalid":"{7B81B066-0551-4FA3-A2FA-8559D4E475EE}","county":"BOULDER","cause":"Outage","city":"Longmont","xcelarea":"Longmont"}},{"type":"Feature","id":52226,"geometry":{"type":"Point","coordinates":[-104.83483144988627,39.692612680328367]},"properties":{"objectid":52226,"boundary":null,"comments":"Crews are working to restore power as quickly and safely as possible. Please continue to check back for estimated restoration time updates. Thank you for your patience.","customers":1,"off_":1766823180000,"etr":1766833200000,"ticket":"27121335","outageimpact":"Small","outagetype":"Unplanned Outage","medialink":null,"outagestatus":0,"datastatus":null,"latlong":"4821373.620700002,-11670160.0544","states":"CO","crewstatus":null,"globalid":"{C3786088-2711-4B75-B776-EE592981C00C}","county":"ARAPAHOE","cause":"Outage","city":"Aurora","xcelarea":"Aurora"}},{"type":"Feature","id":52356,"geometry":{"type":"Point","coordinates":[-91.275008779630127,43.972169310152701]},"properties":{"objectid":52356,"boundary":null,"comments":"Crews are working to restore power as quickly and safely as possible. Please continue to check back for estimated restoration time updates. Thank you for your patience.","customers":1,"off_":1766838900000,"etr":1766845800000,"ticket":"27121335","outageimpact":"Small","outagetype":"Unplanned Outage","medialink":null,"outagestatus":0,"datastatus":null,"latlong":"5461136.329599999,-10160687.4995","states":"WI","crewstatus":null,"globalid":"{26FA878B-3080-4B98-9F11-DD401AAA482A}","county":"LA CROSSE","cause":"Outage","city":"Holmen","xcelarea":"Holmen"}},{"type":"Feature","id":52258,"geometry":{"type":"Point","coordinates":[-105.07614110023209,40.348161839799019]},"properties":{"objectid":52258,"boundary":null,"comments":"Crews are in the area working to restore power as quickly and safely as possible. Please continue to check back for estimated restoration time updates. Thank you for your patience.","customers":1,"off_":1766827740000,"etr":null,"ticket":"27121335","outageimpact":"Small","outagetype":"Unplanned Outage","medialink":null,"outagestatus":0,"datastatus":null,"latlong":"4916665.948100001,-11697022.5218","states":"CO","crewstatus":null,"globalid":"{D2140072-5CA6-4BBB-9932-D41369DFD15E}","county":"LARIMER","cause":"Outage","city":"Loveland","xcelarea":"Loveland"}},{"type":"Feature","id":52358,"geometry":{"type":"Point","coordinates":[-104.8882698096704,39.744200710345297]},"properties":{"objectid":52358,"boundary":null,"comments":"Crews are working to restore power as quickly and safely as possible. Please continue to check back for estimated restoration time updates. Thank you for your patience.","customers":11,"off_":1766835840000,"etr":1766840400000,"ticket":"27121335","outageimpact":"Small","outagetype":"Unplanned Outage","medialink":null,"outagestatus":0,"datastatus":null,"latlong":"4828839.554399997,-11676108.7854","states":"CO","crewstatus":null,"globalid":"{D53A21AC-0A97-45DC-BBC6-F2C8F6F241D9}","county":"DENVER","cause":"Outage","city":"Denver","xcelarea":"Denver"}},{"type":"Feature","id":52346,"geometry":{"type":"Point","coordinates":[-104.74747738968797,40.411523200035738]},"properties":{"objectid":52346,"boundary":null,"comments":"Crews are working to restore power as quickly and safely as possible. Please continue to check back for estimated restoration time updates. Thank you for your patience.","customers":333,"off_":1766833920000,"etr":1766837700000,"ticket":"27121335","outageimpact":"Medium","outagetype":"Unplanned Outage","medialink":null,"outagestatus":0,"datastatus":null,"latlong":"4925925.1598000005,-11660435.8449","states":"CO","crewstatus":null,"globalid":"{6D01AE64-9BFC-4D11-AD44-80ACDD267017}","county":"WELD","cause":"Outage","city":"Greeley","xcelarea":"Greeley"}},{"type":"Feature","id":52366,"geometry":{"type":"Point","coordinates":[-104.44338972041481,33.306185579994029]},"properties":{"objectid":52366,"boundary":null,"comments":"The outage has been reported. Please continue to check back for additional updates regarding the restoration progress.","customers":1,"off_":1766837460000,"etr":1766848500000,"ticket":"27121335","outageimpact":"Small","outagetype":"Unplanned Outage","medialink":null,"outagestatus":0,"datastatus":null,"latlong":"3936015.856200002,-11626584.9604","states":"NM","crewstatus":null,"globalid":"{890D4562-D31D-4B45-8F1E-B61C1D0E6191}","county":"CHAVES-OUT","cause":"Outage","city":"Roswell","xcelarea":"Roswell"}},{"type":"Feature","id":52318,"geometry":{"type":"Point","coordinates":[-93.181516600386558,44.848122209779433]},"properties":{"objectid":52318,"boundary":null,"comments":"Crews are in the area working to restore power as quickly and safely as possible. Please continue to check back for estimated restoration time updates. Thank you for your patience.","customers":1,"off_":1766834160000,"etr":1766844000000,"ticket":"27121335","outageimpact":"Small","outagetype":"Unplanned Outage","medialink":null,"outagestatus":0,"datastatus":null,"latlong":"5597643.0427,-10372918.9793","states":"MN","crewstatus":"Crew Onsite","globalid":"{806EF544-3D3D-4B2A-9F20-33BF9BB06D04}","county":"DAKOTA","cause":"Outage","city":"Eagan","xcelarea":"Eagan"}},{"type":"Feature","id":52247,"geometry":{"type":"Point","coordinates":[-92.838523550131725,44.039077989706939]},"properties":{"objectid":52247,"boundary":null,"comments":"Crews are working to restore power as quickly and safely as possible. Please continue to check back for estimated restoration time updates. Thank you for your patience.","customers":1,"off_":1766830080000,"etr":1766836800000,"ticket":"27121335","outageimpact":"Small","outagetype":"Unplanned Outage","medialink":null,"outagestatus":0,"datastatus":null,"latlong":"5471491.585100003,-10334737.1676","states":"MN","crewstatus":null,"globalid":"{386C1E00-E668-4448-BD1C-8014D49CA39A}","county":"DODGE","cause":"Outage","city":"Dodge Center","xcelarea":"Dodge Center"}},{"type":"Feature","id":52340,"geometry":{"type":"Point","coordinates":[-93.386193840083166,44.917030190225191]},"properties":{"objectid":52340,"boundary":null,"comments":"Crews are working to restore power as quickly and safely as possible. Please continue to check back for estimated restoration time updates. Thank you for your patience.","customers":6,"off_":1766836440000,"etr":1766844000000,"ticket":"27121335","outageimpact":"Small","outagetype":"Unplanned Outage","medialink":null,"outagestatus":0,"datastatus":null,"latlong":"5608469.031499997,-10395703.5454","states":"MN","crewstatus":null,"globalid":"{F9757C1C-F2C5-44D4-93F7-DEB3C6145E2C}","county":"HENNEPIN","cause":"Outage","city":"Edina","xcelarea":"Edina"}},{"type":"Feature","id":52349,"geometry":{"type":"Point","coordinates":[-105.0291373800146,39.962776650083519]},"properties":{"objectid":52349,"boundary":null,"comments":"Crews are working to restore power as quickly and safely as possible. Please continue to check back for estimated restoration time updates. Thank you for your patience.","customers":2,"off_":1766834640000,"etr":1766842200000,"ticket":"27121335","outageimpact":"Small","outagetype":"Unplanned Outage","medialink":null,"outagestatus":0,"datastatus":null,"latlong":"4860534.5572,-11691790.0916","states":"CO","crewstatus":null,"globalid":"{7CBB5DCA-4EBF-4E88-92DC-2F3F024460EB}","county":"BROOMFIELD","cause":"Outage","city":"Broomfield","xcelarea":"Broomfield"}}]}